ol_openedx_course_export/__init__.py
ol_openedx_course_export/app.py
ol_openedx_course_export/constants.py
ol_openedx_course_export/s3_client.py
ol_openedx_course_export/tasks.py
ol_openedx_course_export/urls.py
ol_openedx_course_export/utils.py
ol_openedx_course_export/views.py
ol_openedx_course_export/settings/__init__.py
ol_openedx_course_export/settings/common.py
ol_openedx_course_export/settings/production.py
ol_openedx_course_export-0.2.0.dist-info/METADATA
ol_openedx_course_export-0.2.0.dist-info/WHEEL
ol_openedx_course_export-0.2.0.dist-info/entry_points.txt
ol_openedx_course_export-0.2.0.dist-info/licenses/LICENSE.txt
ol_openedx_course_export-0.2.0.dist-info/RECORD
