Metadata-Version: 2.4
Name: ol-openedx-course-export
Version: 0.2.0
Summary: An Open edX plugin to add API for course export to s3
Author: MIT Office of Digital Learning
License-Expression: BSD-3-Clause
License-File: LICENSE.txt
Requires-Python: >=3.11
Requires-Dist: celery>=4.4.7
Requires-Dist: django>=4.0
Requires-Dist: djangorestframework>=3.14.0
Requires-Dist: edx-django-utils>4.0.0
Requires-Dist: edx-drf-extensions>=10.0.0
Requires-Dist: edx-opaque-keys
